boltiotai/__init__.py
boltiotai/_client.py
boltiotai/_request.py
boltiotai/resources/__init__.py
boltiotai/resources/images.py
boltiotai/resources/chat/__init__.py
boltiotai/resources/chat/chat.py
boltiotai/resources/chat/completions.py
boltiotai-0.0.3.dist-info/LICENSE
boltiotai-0.0.3.dist-info/METADATA
boltiotai-0.0.3.dist-info/WHEEL
boltiotai-0.0.3.dist-info/top_level.txt
boltiotai-0.0.3.dist-info/RECORD
