Metadata-Version: 2.1
Name: boltiotai
Version: 0.0.3
Summary: A package for managing API access to LLMs
Author-email: Pranav Kundaikar <support@boltiot.com>
Classifier: Programming Language :: Python :: 3
Classifier: License :: OSI Approved :: MIT License
Classifier: Operating System :: OS Independent
Requires-Python: >=3.8
License-File: LICENSE
Requires-Dist: requests
